classy_imaginary/Caption.py
classy_imaginary/FixFaces.py
classy_imaginary/Imagine.py
classy_imaginary/Upscaler.py
classy_imaginary/__init__.py
classy_imaginary/animations.py
classy_imaginary/api.py
classy_imaginary/bin/aimg
classy_imaginary/bin/imagine
classy_imaginary/cli/__init__.py
classy_imaginary/cli/colorize.py
classy_imaginary/cli/describe.py
classy_imaginary/cli/edit.py
classy_imaginary/cli/edit_demo.py
classy_imaginary/cli/imagine.py
classy_imaginary/cli/main.py
classy_imaginary/cli/shared.py
classy_imaginary/cli/train.py
classy_imaginary/cli/upscale.py
classy_imaginary/colorize.py
classy_imaginary/config.py
classy_imaginary/configs/control-net-v15.yaml
classy_imaginary/configs/graphicArt_graphicArtBeta.yaml
classy_imaginary/configs/instruct-pix2pix.yaml
classy_imaginary/configs/realismEngine_v10.yaml
classy_imaginary/configs/stable-diffusion-v1-inpaint.yaml
classy_imaginary/configs/stable-diffusion-v1.yaml
classy_imaginary/configs/stable-diffusion-v2-inference-v.yaml
classy_imaginary/configs/stable-diffusion-v2-inference.yaml
classy_imaginary/configs/stable-diffusion-v2-inpainting-inference.yaml
classy_imaginary/configs/stable-diffusion-v2-midas-inference.yaml
classy_imaginary/configs/stable-diffusion-v2-modern-buildings.yaml
classy_imaginary/configs/stable-diffusion-x4-upscaling.yaml
classy_imaginary/data/DejaVuSans.ttf
classy_imaginary/debug_info.py
classy_imaginary/enhancers/__init__.py
classy_imaginary/enhancers/blur_detect.py
classy_imaginary/enhancers/bool_masker.py
classy_imaginary/enhancers/clip_masking.py
classy_imaginary/enhancers/describe_image_blip.py
classy_imaginary/enhancers/describe_image_clip.py
classy_imaginary/enhancers/face_restoration_codeformer.py
classy_imaginary/enhancers/facecrop.py
classy_imaginary/enhancers/phraselists/__init__.py
classy_imaginary/enhancers/phraselists/art-scene.txt
classy_imaginary/enhancers/phraselists/color.txt
classy_imaginary/enhancers/phraselists/desktop-background.txt
classy_imaginary-0.6.5.dist-info/LICENSE
classy_imaginary-0.6.5.dist-info/METADATA
classy_imaginary-0.6.5.dist-info/WHEEL
classy_imaginary-0.6.5.dist-info/RECORD
