Metadata-Version: 2.1
Name: classy-imaginary
Version: 0.6.5
Summary: This is not a useful package. It is a wrapper around imaginary to provide a Class interface.
Author: Hanoush
Author-email: hanoush87@gmail.com
Requires-Python: >=3.9,<4.0
Classifier: Programming Language :: Python :: 3
Classifier: Programming Language :: Python :: 3.9
Classifier: Programming Language :: Python :: 3.10
Classifier: Programming Language :: Python :: 3.11
Requires-Dist: imaginAIry (==11.1.0)
